{
  "count": 2,
  "items": [
    {
      "album_id": -6,
      "date": 1665987065,
      "id": 457243643,
      "owner_id": 372017665,
      "post_id": 236,
      "sizes": [
        {
          "height": 72,
          "type": "s",
          "width": 72,
          "url": "https://sun9-34.userapi.com/s/v1/ig2/fbN27p2ds3Q-UXQxizNt6zh6NHE6eg8IL-ukuZfOdAcJCUMmI2rgSJFcQU1wJDtUja3_NWfub4zcGpSyovRWj0B7.jpg?quality=95&as=32x32,48x48,72x72,108x108,160x160,240x240,360x360,480x480,540x540,640x640,720x720,1080x1080,1280x1280,1440x1440,2448x2448&from=bu&u=BE99LXopepvyNmieNUq-MNeyI7oNF5yNG8GEP5-jM9g&cs=72x0"
        },
        {
          "height": 160,
          "type": "m",
          "width": 160,
          "url": "https://sun9-34.userapi.com/s/v1/ig2/fbN27p2ds3Q-UXQxizNt6zh6NHE6eg8IL-ukuZfOdAcJCUMmI2rgSJFcQU1wJDtUja3_NWfub4zcGpSyovRWj0B7.jpg?quality=95&as=32x32,48x48,72x72,108x108,160x160,240x240,360x360,480x480,540x540,640x640,720x720,1080x1080,1280x1280,1440x1440,2448x2448&from=bu&u=BE99LXopepvyNmieNUq-MNeyI7oNF5yNG8GEP5-jM9g&cs=160x0"
        },
        {
          "height": 640,
          "type": "x",
          "width": 640,
          "url": "https://sun9-34.userapi.com/s/v1/ig2/fbN27p2ds3Q-UXQxizNt6zh6NHE6eg8IL-ukuZfOdAcJCUMmI2rgSJFcQU1wJDtUja3_NWfub4zcGpSyovRWj0B7.jpg?quality=95&as=32x32,48x48,72x72,108x108,160x160,240x240,360x360,480x480,540x540,640x640,720x720,1080x1080,1280x1280,1440x1440,2448x2448&from=bu&u=BE99LXopepvyNmieNUq-MNeyI7oNF5yNG8GEP5-jM9g&cs=640x0"
        },
        {
          "height": 1080,
          "type": "y",
          "width": 1080,
          "url": "https://sun9-34.userapi.com/s/v1/ig2/fbN27p2ds3Q-UXQxizNt6zh6NHE6eg8IL-ukuZfOdAcJCUMmI2rgSJFcQU1wJDtUja3_NWfub4zcGpSyovRWj0B7.jpg?quality=95&as=32x32,48x48,72x72,108x108,160x160,240x240,360x360,480x480,540x540,640x640,720x720,1080x1080,1280x1280,1440x1440,2448x2448&from=bu&u=BE99LXopepvyNmieNUq-MNeyI7oNF5yNG8GEP5-jM9g&cs=1080x0"
        },
        {
          "height": 1280,
          "type": "z",
          "width": 1280,
          "url": "https://sun9-34.userapi.com/s/v1/ig2/fbN27p2ds3Q-UXQxizNt6zh6NHE6eg8IL-ukuZfOdAcJCUMmI2rgSJFcQU1wJDtUja3_NWfub4zcGpSyovRWj0B7.jpg?quality=95&as=32x32,48x48,72x72,108x108,160x160,240x240,360x360,480x480,540x540,640x640,720x720,1080x1080,1280x1280,1440x1440,2448x2448&from=bu&u=BE99LXopepvyNmieNUq-MNeyI7oNF5yNG8GEP5-jM9g&cs=1280x0"
        },
        {
          "height": 2448,
          "type": "w",
          "width": 2448,
          "url": "https://sun9-34.userapi.com/s/v1/ig2/fbN27p2ds3Q-UXQxizNt6zh6NHE6eg8IL-ukuZfOdAcJCUMmI2rgSJFcQU1wJDtUja3_NWfub4zcGpSyovRWj0B7.jpg?quality=95&as=32x32,48x48,72x72,108x108,160x160,240x240,360x360,480x480,540x540,640x640,720x720,1080x1080,1280x1280,1440x1440,2448x2448&from=bu&u=BE99LXopepvyNmieNUq-MNeyI7oNF5yNG8GEP5-jM9g&cs=2448x0"
        },
        {
          "height": 108,
          "type": "o",
          "width": 108,
          "url": "https://sun9-34.userapi.com/s/v1/ig2/fbN27p2ds3Q-UXQxizNt6zh6NHE6eg8IL-ukuZfOdAcJCUMmI2rgSJFcQU1wJDtUja3_NWfub4zcGpSyovRWj0B7.jpg?quality=95&as=32x32,48x48,72x72,108x108,160x160,240x240,360x360,480x480,540x540,640x640,720x720,1080x1080,1280x1280,1440x1440,2448x2448&from=bu&u=BE99LXopepvyNmieNUq-MNeyI7oNF5yNG8GEP5-jM9g&cs=108x0"
        },
        {
          "height": 240,
          "type": "p",
          "width": 240,
          "url": "https://sun9-34.userapi.com/s/v1/ig2/fbN27p2ds3Q-UXQxizNt6zh6NHE6eg8IL-ukuZfOdAcJCUMmI2rgSJFcQU1wJDtUja3_NWfub4zcGpSyovRWj0B7.jpg?quality=95&as=32x32,48x48,72x72,108x108,160x160,240x240,360x360,480x480,540x540,640x640,720x720,1080x1080,1280x1280,1440x1440,2448x2448&from=bu&u=BE99LXopepvyNmieNUq-MNeyI7oNF5yNG8GEP5-jM9g&cs=240x0"
        },
        {
          "height": 360,
          "type": "q",
          "width": 360,
          "url": "https://sun9-34.userapi.com/s/v1/ig2/fbN27p2ds3Q-UXQxizNt6zh6NHE6eg8IL-ukuZfOdAcJCUMmI2rgSJFcQU1wJDtUja3_NWfub4zcGpSyovRWj0B7.jpg?quality=95&as=32x32,48x48,72x72,108x108,160x160,240x240,360x360,480x480,540x540,640x640,720x720,1080x1080,1280x1280,1440x1440,2448x2448&from=bu&u=BE99LXopepvyNmieNUq-MNeyI7oNF5yNG8GEP5-jM9g&cs=360x0"
        },
        {
          "height": 540,
          "type": "r",
          "width": 540,
          "url": "https://sun9-34.userapi.com/s/v1/ig2/fbN27p2ds3Q-UXQxizNt6zh6NHE6eg8IL-ukuZfOdAcJCUMmI2rgSJFcQU1wJDtUja3_NWfub4zcGpSyovRWj0B7.jpg?quality=95&as=32x32,48x48,72x72,108x108,160x160,240x240,360x360,480x480,540x540,640x640,720x720,1080x1080,1280x1280,1440x1440,2448x2448&from=bu&u=BE99LXopepvyNmieNUq-MNeyI7oNF5yNG8GEP5-jM9g&cs=540x0"
        },
        {
          "height": 2448,
          "type": "base",
          "width": 2448,
          "url": "https://sun9-34.userapi.com/s/v1/ig2/fbN27p2ds3Q-UXQxizNt6zh6NHE6eg8IL-ukuZfOdAcJCUMmI2rgSJFcQU1wJDtUja3_NWfub4zcGpSyovRWj0B7.jpg?quality=95&as=32x32,48x48,72x72,108x108,160x160,240x240,360x360,480x480,540x540,640x640,720x720,1080x1080,1280x1280,1440x1440,2448x2448&from=bu&u=BE99LXopepvyNmieNUq-MNeyI7oNF5yNG8GEP5-jM9g"
        }
      ],
      "square_crop": "346,210,1222",
      "text": "",
      "web_view_token": "99e86a94c98af5727d",
      "has_tags": false,
      "likes": {
        "count": 98,
        "user_likes": 0
      },
      "reposts": {
        "count": 0
      },
      "orig_photo": {
        "height": 2448,
        "type": "base",
        "url": "https://sun9-34.userapi.com/s/v1/ig2/fbN27p2ds3Q-UXQxizNt6zh6NHE6eg8IL-ukuZfOdAcJCUMmI2rgSJFcQU1wJDtUja3_NWfub4zcGpSyovRWj0B7.jpg?quality=95&as=32x32,48x48,72x72,108x108,160x160,240x240,360x360,480x480,540x540,640x640,720x720,1080x1080,1280x1280,1440x1440,2448x2448&from=bu&u=BE99LXopepvyNmieNUq-MNeyI7oNF5yNG8GEP5-jM9g",
        "width": 2448
      }
    },
    {
      "album_id": -6,
      "date": 1645784562,
      "id": 457243367,
      "owner_id": 372017665,
      "post_id": 230,
      "sizes": [
        {
          "height": 156,
          "type": "s",
          "width": 72,
          "url": "https://sun9-8.userapi.com/s/v1/ig2/9HJnpoO0Op1Zw_LASA6zDpcDN5K85rPlvKdUnfimbcHT3sxVtpxyM2L90noMJ0GQ2kwuGfPAYhA-mHdc1ryajIog.jpg?quality=95&as=32x69,48x104,72x156,108x234,160x347,240x520,360x780,480x1040,540x1170,640x1387,720x1560,886x1920&from=bu&u=sT53w5h1Nx6liDSL-mCadcVW_WskrU5Gax9iO1mhD_4&cs=72x0"
        },
        {
          "height": 347,
          "type": "m",
          "width": 160,
          "url": "https://sun9-8.userapi.com/s/v1/ig2/9HJnpoO0Op1Zw_LASA6zDpcDN5K85rPlvKdUnfimbcHT3sxVtpxyM2L90noMJ0GQ2kwuGfPAYhA-mHdc1ryajIog.jpg?quality=95&as=32x69,48x104,72x156,108x234,160x347,240x520,360x780,480x1040,540x1170,640x1387,720x1560,886x1920&from=bu&u=sT53w5h1Nx6liDSL-mCadcVW_WskrU5Gax9iO1mhD_4&cs=160x0"
        },
        {
          "height": 1387,
          "type": "x",
          "width": 640,
          "url": "https://sun9-8.userapi.com/s/v1/ig2/9HJnpoO0Op1Zw_LASA6zDpcDN5K85rPlvKdUnfimbcHT3sxVtpxyM2L90noMJ0GQ2kwuGfPAYhA-mHdc1ryajIog.jpg?quality=95&as=32x69,48x104,72x156,108x234,160x347,240x520,360x780,480x1040,540x1170,640x1387,720x1560,886x1920&from=bu&u=sT53w5h1Nx6liDSL-mCadcVW_WskrU5Gax9iO1mhD_4&cs=640x0"
        },
        {
          "height": 1920,
          "type": "y",
          "width": 886,
          "url": "https://sun9-8.userapi.com/s/v1/ig2/9HJnpoO0Op1Zw_LASA6zDpcDN5K85rPlvKdUnfimbcHT3sxVtpxyM2L90noMJ0GQ2kwuGfPAYhA-mHdc1ryajIog.jpg?quality=95&as=32x69,48x104,72x156,108x234,160x347,240x520,360x780,480x1040,540x1170,640x1387,720x1560,886x1920&from=bu&u=sT53w5h1Nx6liDSL-mCadcVW_WskrU5Gax9iO1mhD_4&cs=886x0"
        },
        {
          "height": 234,
          "type": "o",
          "width": 108,
          "url": "https://sun9-8.userapi.com/s/v1/ig2/9HJnpoO0Op1Zw_LASA6zDpcDN5K85rPlvKdUnfimbcHT3sxVtpxyM2L90noMJ0GQ2kwuGfPAYhA-mHdc1ryajIog.jpg?quality=95&as=32x69,48x104,72x156,108x234,160x347,240x520,360x780,480x1040,540x1170,640x1387,720x1560,886x1920&from=bu&u=sT53w5h1Nx6liDSL-mCadcVW_WskrU5Gax9iO1mhD_4&cs=108x0"
        },
        {
          "height": 520,
          "type": "p",
          "width": 240,
          "url": "https://sun9-8.userapi.com/s/v1/ig2/9HJnpoO0Op1Zw_LASA6zDpcDN5K85rPlvKdUnfimbcHT3sxVtpxyM2L90noMJ0GQ2kwuGfPAYhA-mHdc1ryajIog.jpg?quality=95&as=32x69,48x104,72x156,108x234,160x347,240x520,360x780,480x1040,540x1170,640x1387,720x1560,886x1920&from=bu&u=sT53w5h1Nx6liDSL-mCadcVW_WskrU5Gax9iO1mhD_4&cs=240x0"
        },
        {
          "height": 780,
          "type": "q",
          "width": 360,
          "url": "https://sun9-8.userapi.com/s/v1/ig2/9HJnpoO0Op1Zw_LASA6zDpcDN5K85rPlvKdUnfimbcHT3sxVtpxyM2L90noMJ0GQ2kwuGfPAYhA-mHdc1ryajIog.jpg?quality=95&as=32x69,48x104,72x156,108x234,160x347,240x520,360x780,480x1040,540x1170,640x1387,720x1560,886x1920&from=bu&u=sT53w5h1Nx6liDSL-mCadcVW_WskrU5Gax9iO1mhD_4&cs=360x0"
        },
        {
          "height": 1170,
          "type": "r",
          "width": 540,
          "url": "https://sun9-8.userapi.com/s/v1/ig2/9HJnpoO0Op1Zw_LASA6zDpcDN5K85rPlvKdUnfimbcHT3sxVtpxyM2L90noMJ0GQ2kwuGfPAYhA-mHdc1ryajIog.jpg?quality=95&as=32x69,48x104,72x156,108x234,160x347,240x520,360x780,480x1040,540x1170,640x1387,720x1560,886x1920&from=bu&u=sT53w5h1Nx6liDSL-mCadcVW_WskrU5Gax9iO1mhD_4&cs=540x0"
        },
        {
          "height": 1920,
          "type": "base",
          "width": 886,
          "url": "https://sun9-8.userapi.com/s/v1/ig2/9HJnpoO0Op1Zw_LASA6zDpcDN5K85rPlvKdUnfimbcHT3sxVtpxyM2L90noMJ0GQ2kwuGfPAYhA-mHdc1ryajIog.jpg?quality=95&as=32x69,48x104,72x156,108x234,160x347,240x520,360x780,480x1040,540x1170,640x1387,720x1560,886x1920&from=bu&u=sT53w5h1Nx6liDSL-mCadcVW_WskrU5Gax9iO1mhD_4"
        }
      ],
      "square_crop": "219,604,442",
      "text": "",
      "web_view_token": "1b0d2248be0eecabc7",
      "has_tags": false,
      "likes": {
        "count": 31,
        "user_likes": 0
      },
      "reposts": {
        "count": 0
      },
      "orig_photo": {
        "height": 1920,
        "type": "base",
        "url": "https://sun9-8.userapi.com/s/v1/ig2/9HJnpoO0Op1Zw_LASA6zDpcDN5K85rPlvKdUnfimbcHT3sxVtpxyM2L90noMJ0GQ2kwuGfPAYhA-mHdc1ryajIog.jpg?quality=95&as=32x69,48x104,72x156,108x234,160x347,240x520,360x780,480x1040,540x1170,640x1387,720x1560,886x1920&from=bu&u=sT53w5h1Nx6liDSL-mCadcVW_WskrU5Gax9iO1mhD_4",
        "width": 886
      }
    }
  ]
}